pyaarlo/__init__.py
pyaarlo/backend.py
pyaarlo/background.py
pyaarlo/base.py
pyaarlo/camera.py
pyaarlo/cfg.py
pyaarlo/constant.py
pyaarlo/device.py
pyaarlo/doorbell.py
pyaarlo/light.py
pyaarlo/location.py
pyaarlo/main.py
pyaarlo/media.py
pyaarlo/ratls.py
pyaarlo/security_utils.py
pyaarlo/sensor.py
pyaarlo/sseclient.py
pyaarlo/storage.py
pyaarlo/super.py
pyaarlo/tfa.py
pyaarlo/util.py
pyaarlo-0.8.0.14.dist-info/LICENSE
pyaarlo-0.8.0.14.dist-info/METADATA
pyaarlo-0.8.0.14.dist-info/WHEEL
pyaarlo-0.8.0.14.dist-info/entry_points.txt
pyaarlo-0.8.0.14.dist-info/top_level.txt
pyaarlo-0.8.0.14.dist-info/RECORD
