Metadata-Version: 2.2
Name: pyaarlo
Version: 0.8.0.14
Summary: PyAarlo is a library that provides asynchronous access to Arlo security cameras.
Home-page: https://github.com/twrecked/pyaarlo.git
Author: Steve Herrell
Author-email: steve.herrell@gmail.com
License: LGPLv3+
Project-URL: Bug Tracker, https://github.com/twrecked/pyaarlo/issues
Project-URL: Documentation, https://github.com/twrecked/pyaarlo/blob/master/README.md
Project-URL: Source Code, https://github.com/twrecked/pyaarlo
Keywords: arlo,netgear,camera,home automation,python
Classifier: Environment :: Other Environment
Classifier: Intended Audience :: Developers
Classifier: License :: OSI Approved :: GNU Lesser General Public License v3 or later (LGPLv3+)
Classifier: Operating System :: OS Independent
Classifier: Programming Language :: Python
Classifier: Programming Language :: Python :: 3.6
Classifier: Programming Language :: Python :: 3.7
Classifier: Programming Language :: Python :: 3.8
Classifier: Programming Language :: Python :: 3.9
Classifier: Topic :: Software Development :: Libraries :: Python Modules
Requires-Python: >=3.7
License-File: LICENSE
Requires-Dist: requests
Requires-Dist: click
Requires-Dist: pycryptodome
Requires-Dist: unidecode
Requires-Dist: cloudscraper>=1.2.71
Requires-Dist: paho-mqtt
Requires-Dist: cryptography
Requires-Dist: python-slugify
Dynamic: author
Dynamic: author-email
Dynamic: classifier
Dynamic: description
Dynamic: description-content-type
Dynamic: home-page
Dynamic: keywords
Dynamic: license
Dynamic: project-url
Dynamic: requires-dist
Dynamic: requires-python
Dynamic: summary
